{
  "project_info": {
    "project_id": "nenfieldassistant",
    "project_number": "269408801054",
    "name": "NENFieldAssistant"
  },
  "client": [
    {
      "client_info": {
        "mobilesdk_app_id": "1:269408801054:android:6f0988716bd71b1c",
        "client_id": "android:nicknestor.nenfieldassistant.activities",
        "client_type": 1,
        "android_client_info": {
          "package_name": "nicknestor.nenfieldassistant.activities"
        }
      },
      "oauth_client": [],
      "api_key": [],
      "services": {
        "analytics_service": {
          "status": 1
        },
        "cloud_messaging_service": {
          "status": 1,
          "apns_config": []
        },
        "appinvite_service": {
          "status": 1,
          "other_platform_oauth_client": []
        },
        "google_signin_service": {
          "status": 1
        },
        "ads_service": {
          "status": 1
        }
      }
    },
    {
      "client_info": {
        "mobilesdk_app_id": "1:269408801054:android:6d45b5408aeac734",
        "client_id": "android:nicknestor.nenfieldassistant",
        "client_type": 1,
        "android_client_info": {
          "package_name": "nicknestor.nenfieldassistant"
        }
      },
      "oauth_client": [
        {
          "client_id": "269408801054-qhvcdvok27smbcm5pln86jlmqrm7l9pa.apps.googleusercontent.com",
          "client_type": 1,
          "android_info": {
            "package_name": "nicknestor.nenfieldassistant",
            "certificate_hash": "D2E7C5B5649C4A6B7743BBA15F7110D1050742CB"
          }
        }
      ],
      "api_key": [],
      "services": {
        "analytics_service": {
          "status": 1
        },
        "cloud_messaging_service": {
          "status": 1,
          "apns_config": []
        },
        "appinvite_service": {
          "status": 1,
          "other_platform_oauth_client": []
        },
        "google_signin_service": {
          "status": 2
        },
        "ads_service": {
          "status": 1
        }
      }
    }
  ],
  "client_info": [],
  "ARTIFACT_VERSION": "1"
}